cuscom/__init__.py
cuscom/exceptions.py
cuscom/utils.py
cuscom/clients/__init__.py
cuscom/clients/base_client.py
cuscom/clients/task_client.py
cuscom/hooks/__init__.py
cuscom/hooks/ms_teams.py
cuscom/hooks/slack.py
cuscom/operators/__init__.py
cuscom/operators/custom_kubernetes_pod_operator.py
cuscom-1.1.1.data/data/VERSION
cuscom-1.1.1.dist-info/LICENSE
cuscom-1.1.1.dist-info/METADATA
cuscom-1.1.1.dist-info/WHEEL
cuscom-1.1.1.dist-info/top_level.txt
cuscom-1.1.1.dist-info/RECORD
