Metadata-Version: 2.1
Name: cuscom
Version: 1.1.1
Summary: Custom components for Airflow
Home-page: https://gitlab.com/greenhousecode/ai/cuscom/
Author: Greenhouse AI team
Author-email: ai@greenhousegroup.com
Classifier: Programming Language :: Python :: 3
Classifier: License :: OSI Approved :: MIT License
Classifier: Operating System :: OS Independent
Classifier: Programming Language :: Python :: 3
License-File: LICENSE
Requires-Dist: apache-airflow[kubernetes,slack] >=2.0.0
